iditarod/__init__.py
iditarod/__main__.py
iditarod/graph_tools.py
iditarod/iditarod.py
iditarod/importqt.py
iditarod/images/icon.png
iditarod/ui/MainWindow.ui
iditarod-1.0.0.dist-info/licenses/LICENSE
iditarod-1.0.0.dist-info/METADATA
iditarod-1.0.0.dist-info/WHEEL
iditarod-1.0.0.dist-info/entry_points.txt
iditarod-1.0.0.dist-info/top_level.txt
iditarod-1.0.0.dist-info/RECORD
