Metadata-Version: 2.4
Name: Iditarod
Version: 1.0.0
Summary: A Shavitt graph visualizer
Author-email: "Ignacio Fdez. Galván" <jellby@yahoo.com>
License:                     GNU GENERAL PUBLIC LICENSE
Project-URL: Homepage, https://gitlab.com/Jellby/Iditarod
Classifier: Development Status :: 5 - Production/Stable
Classifier: Intended Audience :: Science/Research
Classifier: Environment :: X11 Applications :: Qt
Classifier: Topic :: Scientific/Engineering :: Chemistry
Classifier: Topic :: Scientific/Engineering :: Visualization
Classifier: Topic :: Multimedia :: Graphics :: 3D Rendering
License-File: LICENSE
Requires-Dist: numpy>=1.9.0
Requires-Dist: VTK>=8.1.0
Requires-Dist: qtpy
Dynamic: license-file
